flask_celeryext_pro/__init__.py
flask_celeryext_pro/_mapping.py
flask_celeryext_pro/app.py
flask_celeryext_pro/ext.py
flask_celeryext_pro/version.py
Flask_CeleryExt_Pro-0.5.0.dist-info/AUTHORS.rst
Flask_CeleryExt_Pro-0.5.0.dist-info/LICENSE
Flask_CeleryExt_Pro-0.5.0.dist-info/METADATA
Flask_CeleryExt_Pro-0.5.0.dist-info/WHEEL
Flask_CeleryExt_Pro-0.5.0.dist-info/top_level.txt
Flask_CeleryExt_Pro-0.5.0.dist-info/RECORD
